rentcast_client/__init__.py
rentcast_client/api_client.py
rentcast_client/api_response.py
rentcast_client/configuration.py
rentcast_client/exceptions.py
rentcast_client/py.typed
rentcast_client/rest.py
rentcast_client/api/__init__.py
rentcast_client/api/default_api.py
rentcast_client/models/__init__.py
rentcast_client/models/market_statistics200_response.py
rentcast_client/models/market_statistics200_response_rental_data.py
rentcast_client/models/market_statistics200_response_rental_data_data_by_bedrooms_inner.py
rentcast_client/models/market_statistics200_response_rental_data_history.py
rentcast_client/models/market_statistics200_response_rental_data_history202309.py
rentcast_client/models/market_statistics200_response_rental_data_history202309_data_by_bedrooms_inner.py
rentcast_client/models/market_statistics200_response_rental_data_history202310.py
rentcast_client/models/market_statistics200_response_rental_data_history202310_data_by_bedrooms_inner.py
rentcast_client/models/market_statistics200_response_rental_data_history202311.py
rentcast_client/models/market_statistics200_response_rental_data_history202311_data_by_bedrooms_inner.py
rentcast_client/models/market_statistics200_response_rental_data_history202312.py
rentcast_client/models/market_statistics200_response_rental_data_history202312_data_by_bedrooms_inner.py
rentcast_client/models/market_statistics200_response_rental_data_history202401.py
rentcast_client/models/market_statistics200_response_rental_data_history202401_data_by_bedrooms_inner.py
rentcast_client/models/market_statistics200_response_rental_data_history202402.py
rentcast_client/models/property_records200_response_inner.py
rentcast_client/models/property_records200_response_inner_features.py
rentcast_client/models/property_records200_response_inner_owner.py
rentcast_client/models/property_records200_response_inner_owner_mailing_address.py
rentcast_client/models/property_records200_response_inner_property_taxes.py
rentcast_client-1.0.4.dist-info/METADATA
rentcast_client-1.0.4.dist-info/WHEEL
rentcast_client-1.0.4.dist-info/top_level.txt
rentcast_client-1.0.4.dist-info/RECORD
